{
    "openapi": "3.0.0",
    "info": {
        "title": "MusicBox API Documentation",
        "description": "API Documentation for MusicBox",
        "contact": {
            "email": "your-email@domain.com"
        },
        "version": "1.0.0"
    },
    "servers": [
        {
            "url": "http://localhost:8000/api",
            "description": "Local API Server"
        }
    ],
    "paths": {
        "/albums": {
            "get": {
                "tags": [
                    "Albums"
                ],
                "summary": "Get list of albums",
                "operationId": "1da83b13e3f02c4fee3c24e70098d603",
                "responses": {
                    "200": {
                        "description": "Successful operation",
                        "content": {
                            "application/json": {
                                "schema": {
                                    "properties": {
                                        "albums": {
                                            "type": "array",
                                            "items": {
                                                "properties": {
                                                    "id": {
                                                        "type": "integer",
                                                        "example": 1
                                                    },
                                                    "title": {
                                                        "type": "string",
                                                        "example": "Album Title"
                                                    },
                                                    "genre": {
                                                        "type": "string",
                                                        "example": "Rock"
                                                    },
                                                    "release_date": {
                                                        "type": "string",
                                                        "format": "date",
                                                        "example": "2023-09-30"
                                                    },
                                                    "artist_id": {
                                                        "type": "integer",
                                                        "example": 1
                                                    }
                                                },
                                                "type": "object"
                                            }
                                        },
                                        "message": {
                                            "type": "string",
                                            "example": "Albums Fetched Successfully"
                                        }
                                    },
                                    "type": "object"
                                }
                            }
                        }
                    }
                },
                "security": [
                    {
                        "bearerAuth": []
                    }
                ]
            }
        },
        "/create-album": {
            "post": {
                "tags": [
                    "Albums"
                ],
                "summary": "Create a new album",
                "operationId": "f3e7d46bee002811849594c2cda55228",
                "requestBody": {
                    "required": true,
                    "content": {
                        "application/json": {
                            "schema": {
                                "required": [
                                    "title",
                                    "genre",
                                    "release_date",
                                    "artist_id"
                                ],
                                "properties": {
                                    "title": {
                                        "type": "string",
                                        "example": "New Album"
                                    },
                                    "genre": {
                                        "type": "string",
                                        "example": "Rock"
                                    },
                                    "release_date": {
                                        "type": "string",
                                        "format": "date",
                                        "example": "2023-09-30"
                                    },
                                    "artist_id": {
                                        "type": "integer",
                                        "example": 1
                                    }
                                },
                                "type": "object"
                            }
                        }
                    }
                },
                "responses": {
                    "201": {
                        "description": "Album created successfully",
                        "content": {
                            "application/json": {
                                "schema": {
                                    "properties": {
                                        "album": {
                                            "type": "object"
                                        },
                                        "message": {
                                            "type": "string",
                                            "example": "Album Created Successfully"
                                        }
                                    },
                                    "type": "object"
                                }
                            }
                        }
                    }
                },
                "security": [
                    {
                        "bearerAuth": []
                    }
                ]
            }
        },
        "/album/{id}": {
            "get": {
                "tags": [
                    "Albums"
                ],
                "summary": "Get album by ID with artist and songs",
                "operationId": "ab99ef3b8af190380c7483bcfedced79",
                "parameters": [
                    {
                        "name": "id",
                        "in": "path",
                        "required": true,
                        "schema": {
                            "type": "integer"
                        }
                    }
                ],
                "responses": {
                    "200": {
                        "description": "Success",
                        "content": {
                            "application/json": {
                                "schema": {
                                    "properties": {
                                        "album": {
                                            "type": "object"
                                        },
                                        "message": {
                                            "type": "string",
                                            "example": "Album Fetched Successfully"
                                        }
                                    },
                                    "type": "object"
                                }
                            }
                        }
                    }
                },
                "security": [
                    {
                        "bearerAuth": []
                    }
                ]
            }
        },
        "/update-album/{id}": {
            "put": {
                "tags": [
                    "Albums"
                ],
                "summary": "Update album",
                "operationId": "4ae591c035ecc603b152e5ccf4ddf220",
                "parameters": [
                    {
                        "name": "id",
                        "in": "path",
                        "required": true,
                        "schema": {
                            "type": "integer"
                        }
                    }
                ],
                "requestBody": {
                    "content": {
                        "application/json": {
                            "schema": {
                                "required": [
                                    "title",
                                    "genre",
                                    "release_date",
                                    "artist_id"
                                ],
                                "properties": {
                                    "title": {
                                        "type": "string",
                                        "example": "Updated Album"
                                    },
                                    "genre": {
                                        "type": "string",
                                        "example": "Pop"
                                    },
                                    "release_date": {
                                        "type": "string",
                                        "format": "date",
                                        "example": "2023-10-01"
                                    },
                                    "artist_id": {
                                        "type": "integer"
                                    }
                                },
                                "type": "object"
                            }
                        }
                    }
                },
                "responses": {
                    "200": {
                        "description": "Success",
                        "content": {
                            "application/json": {
                                "schema": {
                                    "properties": {
                                        "album": {
                                            "type": "object"
                                        },
                                        "message": {
                                            "type": "string",
                                            "example": "Album Updated Successfully"
                                        }
                                    },
                                    "type": "object"
                                }
                            }
                        }
                    }
                },
                "security": [
                    {
                        "bearerAuth": []
                    }
                ]
            }
        },
        "/delete-album/{id}": {
            "delete": {
                "tags": [
                    "Albums"
                ],
                "summary": "Delete album",
                "operationId": "06bb149ec22d0b46a709d26d6f82111a",
                "parameters": [
                    {
                        "name": "id",
                        "in": "path",
                        "required": true,
                        "schema": {
                            "type": "integer"
                        }
                    }
                ],
                "responses": {
                    "200": {
                        "description": "Success",
                        "content": {
                            "application/json": {
                                "schema": {
                                    "properties": {
                                        "message": {
                                            "type": "string",
                                            "example": "Album Deleted Successfully"
                                        }
                                    },
                                    "type": "object"
                                }
                            }
                        }
                    }
                },
                "security": [
                    {
                        "bearerAuth": []
                    }
                ]
            }
        },
        "/artists": {
            "get": {
                "tags": [
                    "Artists"
                ],
                "summary": "Get list of artists",
                "operationId": "392d5b22a13c0e6acda09059973b671b",
                "parameters": [
                    {
                        "name": "genre",
                        "in": "query",
                        "description": "Filter artists by genre",
                        "required": false,
                        "schema": {
                            "type": "string"
                        }
                    }
                ],
                "responses": {
                    "200": {
                        "description": "Successful operation",
                        "content": {
                            "application/json": {
                                "schema": {
                                    "properties": {
                                        "artists": {
                                            "properties": {
                                                "data": {
                                                    "type": "array",
                                                    "items": {
                                                        "properties": {
                                                            "id": {
                                                                "type": "integer",
                                                                "example": 1
                                                            },
                                                            "name": {
                                                                "type": "string",
                                                                "example": "Artist Name"
                                                            },
                                                            "genre": {
                                                                "type": "string",
                                                                "example": "Rock"
                                                            },
                                                            "country": {
                                                                "type": "string",
                                                                "example": "USA"
                                                            }
                                                        },
                                                        "type": "object"
                                                    }
                                                }
                                            },
                                            "type": "object"
                                        },
                                        "message": {
                                            "type": "string",
                                            "example": "Artists Fetched Successfully"
                                        }
                                    },
                                    "type": "object"
                                }
                            }
                        }
                    }
                },
                "security": [
                    {
                        "bearerAuth": []
                    }
                ]
            }
        },
        "/create-artist": {
            "post": {
                "tags": [
                    "Artists"
                ],
                "summary": "Create a new artist",
                "operationId": "c7f80ff9dcd689f3c5d4a4a9438917fe",
                "requestBody": {
                    "required": true,
                    "content": {
                        "application/json": {
                            "schema": {
                                "required": [
                                    "name",
                                    "genre",
                                    "country"
                                ],
                                "properties": {
                                    "name": {
                                        "type": "string",
                                        "example": "New Artist"
                                    },
                                    "genre": {
                                        "type": "string",
                                        "example": "Rock"
                                    },
                                    "country": {
                                        "type": "string",
                                        "example": "France"
                                    }
                                },
                                "type": "object"
                            }
                        }
                    }
                },
                "responses": {
                    "201": {
                        "description": "Artist created successfully",
                        "content": {
                            "application/json": {
                                "schema": {
                                    "properties": {
                                        "artist": {
                                            "properties": {
                                                "id": {
                                                    "type": "integer",
                                                    "example": 1
                                                },
                                                "name": {
                                                    "type": "string",
                                                    "example": "New Artist"
                                                },
                                                "genre": {
                                                    "type": "string",
                                                    "example": "Rock"
                                                },
                                                "country": {
                                                    "type": "string",
                                                    "example": "France"
                                                }
                                            },
                                            "type": "object"
                                        },
                                        "message": {
                                            "type": "string",
                                            "example": "Artist Created Successfully"
                                        }
                                    },
                                    "type": "object"
                                }
                            }
                        }
                    },
                    "422": {
                        "description": "Validation error"
                    }
                },
                "security": [
                    {
                        "bearerAuth": []
                    }
                ]
            }
        },
        "/artist/{id}": {
            "get": {
                "tags": [
                    "Artists"
                ],
                "summary": "Get artist by ID with their albums and songs",
                "operationId": "f164438c9b930628a2855c67cd17d8db",
                "parameters": [
                    {
                        "name": "id",
                        "in": "path",
                        "description": "Artist ID",
                        "required": true,
                        "schema": {
                            "type": "integer"
                        }
                    }
                ],
                "responses": {
                    "200": {
                        "description": "Success",
                        "content": {
                            "application/json": {
                                "schema": {
                                    "properties": {
                                        "artist": {
                                            "properties": {
                                                "id": {
                                                    "type": "integer",
                                                    "example": 1
                                                },
                                                "name": {
                                                    "type": "string",
                                                    "example": "Artist Name"
                                                },
                                                "genre": {
                                                    "type": "string",
                                                    "example": "Rock"
                                                },
                                                "country": {
                                                    "type": "string",
                                                    "example": "USA"
                                                },
                                                "albums": {
                                                    "type": "array",
                                                    "items": {
                                                        "properties": {
                                                            "id": {
                                                                "type": "integer",
                                                                "example": 1
                                                            },
                                                            "title": {
                                                                "type": "string",
                                                                "example": "Album Title"
                                                            },
                                                            "songs": {
                                                                "type": "array",
                                                                "items": {
                                                                    "properties": {
                                                                        "id": {
                                                                            "type": "integer",
                                                                            "example": 1
                                                                        },
                                                                        "title": {
                                                                            "type": "string",
                                                                            "example": "Song Title"
                                                                        }
                                                                    },
                                                                    "type": "object"
                                                                }
                                                            }
                                                        },
                                                        "type": "object"
                                                    }
                                                }
                                            },
                                            "type": "object"
                                        },
                                        "message": {
                                            "type": "string",
                                            "example": "Artist Fetched Successfully"
                                        }
                                    },
                                    "type": "object"
                                }
                            }
                        }
                    },
                    "404": {
                        "description": "Artist not found"
                    }
                },
                "security": [
                    {
                        "bearerAuth": []
                    }
                ]
            }
        },
        "/update-artist/{id}": {
            "put": {
                "tags": [
                    "Artists"
                ],
                "summary": "Update existing artist",
                "operationId": "ad64eeb4f8c481e4e17e13c9d0b1bd54",
                "parameters": [
                    {
                        "name": "id",
                        "in": "path",
                        "description": "Artist ID",
                        "required": true,
                        "schema": {
                            "type": "integer"
                        }
                    }
                ],
                "requestBody": {
                    "required": true,
                    "content": {
                        "application/json": {
                            "schema": {
                                "required": [
                                    "name",
                                    "genre",
                                    "country"
                                ],
                                "properties": {
                                    "name": {
                                        "type": "string",
                                        "example": "Updated Artist Name"
                                    },
                                    "genre": {
                                        "type": "string",
                                        "example": "Jazz"
                                    },
                                    "country": {
                                        "type": "string",
                                        "example": "France"
                                    }
                                },
                                "type": "object"
                            }
                        }
                    }
                },
                "responses": {
                    "200": {
                        "description": "Artist updated successfully",
                        "content": {
                            "application/json": {
                                "schema": {
                                    "properties": {
                                        "artist": {
                                            "type": "object"
                                        },
                                        "message": {
                                            "type": "string",
                                            "example": "Artist Updated Successfully"
                                        }
                                    },
                                    "type": "object"
                                }
                            }
                        }
                    },
                    "404": {
                        "description": "Artist not found"
                    }
                },
                "security": [
                    {
                        "bearerAuth": []
                    }
                ]
            }
        },
        "/delete-artist/{id}": {
            "delete": {
                "tags": [
                    "Artists"
                ],
                "summary": "Delete an artist",
                "operationId": "01bfcdaca6f04274b6ddcedd5806f652",
                "parameters": [
                    {
                        "name": "id",
                        "in": "path",
                        "description": "Artist ID",
                        "required": true,
                        "schema": {
                            "type": "integer"
                        }
                    }
                ],
                "responses": {
                    "200": {
                        "description": "Artist deleted successfully",
                        "content": {
                            "application/json": {
                                "schema": {
                                    "properties": {
                                        "message": {
                                            "type": "string",
                                            "example": "Artist Deleted Successfully"
                                        }
                                    },
                                    "type": "object"
                                }
                            }
                        }
                    },
                    "404": {
                        "description": "Artist not found"
                    }
                },
                "security": [
                    {
                        "bearerAuth": []
                    }
                ]
            }
        },
        "/login": {
            "post": {
                "tags": [
                    "Authentication"
                ],
                "summary": "Login user",
                "operationId": "42f77e072dec84b0e1094cca1228298e",
                "requestBody": {
                    "required": true,
                    "content": {
                        "application/json": {
                            "schema": {
                                "required": [
                                    "email",
                                    "password"
                                ],
                                "properties": {
                                    "email": {
                                        "type": "string",
                                        "format": "email",
                                        "example": "user@example.com"
                                    },
                                    "password": {
                                        "type": "string",
                                        "format": "password",
                                        "example": "password123"
                                    }
                                },
                                "type": "object"
                            }
                        }
                    }
                },
                "responses": {
                    "200": {
                        "description": "Login successful",
                        "content": {
                            "application/json": {
                                "schema": {
                                    "properties": {
                                        "user": {
                                            "type": "object"
                                        },
                                        "token": {
                                            "type": "string",
                                            "example": "1|laravel_sanctum_token..."
                                        }
                                    },
                                    "type": "object"
                                }
                            }
                        }
                    },
                    "401": {
                        "description": "Invalid credentials"
                    }
                }
            }
        },
        "/logout": {
            "post": {
                "tags": [
                    "Authentication"
                ],
                "summary": "Logout user",
                "operationId": "03afb12b342c2ea43bdc1de4f39e91a8",
                "responses": {
                    "200": {
                        "description": "Logout successful",
                        "content": {
                            "application/json": {
                                "schema": {
                                    "properties": {
                                        "message": {
                                            "type": "string",
                                            "example": "Logged out successfully"
                                        }
                                    },
                                    "type": "object"
                                }
                            }
                        }
                    }
                },
                "security": [
                    {
                        "bearerAuth": []
                    }
                ]
            }
        },
        "/register": {
            "post": {
                "tags": [
                    "Authentication"
                ],
                "summary": "Register new user",
                "operationId": "573de1fed352c1205a32c4d1b9877375",
                "requestBody": {
                    "required": true,
                    "content": {
                        "application/json": {
                            "schema": {
                                "required": [
                                    "name",
                                    "email",
                                    "password",
                                    "password_confirmation"
                                ],
                                "properties": {
                                    "name": {
                                        "type": "string",
                                        "example": "John Doe"
                                    },
                                    "email": {
                                        "type": "string",
                                        "format": "email",
                                        "example": "user@example.com"
                                    },
                                    "password": {
                                        "type": "string",
                                        "format": "password",
                                        "example": "password123"
                                    },
                                    "password_confirmation": {
                                        "type": "string",
                                        "format": "password",
                                        "example": "password123"
                                    }
                                },
                                "type": "object"
                            }
                        }
                    }
                },
                "responses": {
                    "201": {
                        "description": "User registered successfully",
                        "content": {
                            "application/json": {
                                "schema": {
                                    "properties": {
                                        "user": {
                                            "type": "object"
                                        },
                                        "token": {
                                            "type": "string",
                                            "example": "1|laravel_sanctum_token..."
                                        }
                                    },
                                    "type": "object"
                                }
                            }
                        }
                    },
                    "422": {
                        "description": "Validation error"
                    }
                }
            }
        },
        "/songs": {
            "get": {
                "tags": [
                    "Songs"
                ],
                "summary": "Get list of songs",
                "operationId": "7cff74aca8adedf68f8a9248996cdc0d",
                "responses": {
                    "200": {
                        "description": "Successful operation",
                        "content": {
                            "application/json": {
                                "schema": {
                                    "properties": {
                                        "songs": {
                                            "type": "array",
                                            "items": {
                                                "properties": {
                                                    "id": {
                                                        "type": "integer",
                                                        "example": 1
                                                    },
                                                    "title": {
                                                        "type": "string",
                                                        "example": "Song Title"
                                                    },
                                                    "duration": {
                                                        "type": "integer",
                                                        "example": 180
                                                    },
                                                    "album_id": {
                                                        "type": "integer",
                                                        "example": 1
                                                    }
                                                },
                                                "type": "object"
                                            }
                                        },
                                        "message": {
                                            "type": "string",
                                            "example": "Songs Fetched Successfully"
                                        }
                                    },
                                    "type": "object"
                                }
                            }
                        }
                    }
                },
                "security": [
                    {
                        "bearerAuth": []
                    }
                ]
            }
        },
        "/create-song": {
            "post": {
                "tags": [
                    "Songs"
                ],
                "summary": "Create a new song",
                "operationId": "70a1519f6ac1b26365be893aa16f177d",
                "requestBody": {
                    "required": true,
                    "content": {
                        "application/json": {
                            "schema": {
                                "required": [
                                    "title",
                                    "duration",
                                    "album_id"
                                ],
                                "properties": {
                                    "title": {
                                        "type": "string",
                                        "example": "New Song"
                                    },
                                    "duration": {
                                        "type": "integer",
                                        "example": 180
                                    },
                                    "album_id": {
                                        "type": "integer",
                                        "example": 1
                                    }
                                },
                                "type": "object"
                            }
                        }
                    }
                },
                "responses": {
                    "201": {
                        "description": "Song created successfully",
                        "content": {
                            "application/json": {
                                "schema": {
                                    "properties": {
                                        "song": {
                                            "type": "object"
                                        },
                                        "message": {
                                            "type": "string",
                                            "example": "Song Created Successfully"
                                        }
                                    },
                                    "type": "object"
                                }
                            }
                        }
                    },
                    "422": {
                        "description": "Validation error"
                    }
                },
                "security": [
                    {
                        "bearerAuth": []
                    }
                ]
            }
        },
        "/song/{id}": {
            "get": {
                "tags": [
                    "Songs"
                ],
                "summary": "Get song by ID with album and artist",
                "operationId": "88601f99bc2f18fd5ae52710abefd37d",
                "parameters": [
                    {
                        "name": "id",
                        "in": "path",
                        "description": "Song ID",
                        "required": true,
                        "schema": {
                            "type": "integer"
                        }
                    }
                ],
                "responses": {
                    "200": {
                        "description": "Success",
                        "content": {
                            "application/json": {
                                "schema": {
                                    "properties": {
                                        "song": {
                                            "properties": {
                                                "id": {
                                                    "type": "integer",
                                                    "example": 1
                                                },
                                                "title": {
                                                    "type": "string",
                                                    "example": "Song Title"
                                                },
                                                "duration": {
                                                    "type": "integer",
                                                    "example": 180
                                                },
                                                "album": {
                                                    "properties": {
                                                        "id": {
                                                            "type": "integer",
                                                            "example": 1
                                                        },
                                                        "title": {
                                                            "type": "string",
                                                            "example": "Album Title"
                                                        },
                                                        "artist": {
                                                            "properties": {
                                                                "id": {
                                                                    "type": "integer",
                                                                    "example": 1
                                                                },
                                                                "name": {
                                                                    "type": "string",
                                                                    "example": "Artist Name"
                                                                }
                                                            },
                                                            "type": "object"
                                                        }
                                                    },
                                                    "type": "object"
                                                }
                                            },
                                            "type": "object"
                                        },
                                        "message": {
                                            "type": "string",
                                            "example": "Song Fetched Successfully"
                                        }
                                    },
                                    "type": "object"
                                }
                            }
                        }
                    },
                    "404": {
                        "description": "Song not found"
                    }
                },
                "security": [
                    {
                        "bearerAuth": []
                    }
                ]
            }
        },
        "/update-song/{id}": {
            "put": {
                "tags": [
                    "Songs"
                ],
                "summary": "Update existing song",
                "operationId": "9d93daa24f36fca0fb2c7b520f658c26",
                "parameters": [
                    {
                        "name": "id",
                        "in": "path",
                        "description": "Song ID",
                        "required": true,
                        "schema": {
                            "type": "integer"
                        }
                    }
                ],
                "requestBody": {
                    "required": true,
                    "content": {
                        "application/json": {
                            "schema": {
                                "properties": {
                                    "title": {
                                        "type": "string",
                                        "example": "Updated Song Title"
                                    },
                                    "duration": {
                                        "type": "integer",
                                        "example": 200
                                    },
                                    "album_id": {
                                        "type": "integer",
                                        "example": 1
                                    }
                                },
                                "type": "object"
                            }
                        }
                    }
                },
                "responses": {
                    "200": {
                        "description": "Song updated successfully",
                        "content": {
                            "application/json": {
                                "schema": {
                                    "properties": {
                                        "song": {
                                            "type": "object"
                                        },
                                        "message": {
                                            "type": "string",
                                            "example": "Song Updated Successfully"
                                        }
                                    },
                                    "type": "object"
                                }
                            }
                        }
                    },
                    "404": {
                        "description": "Song not found"
                    }
                },
                "security": [
                    {
                        "bearerAuth": []
                    }
                ]
            }
        },
        "/delete-song/{id}": {
            "delete": {
                "tags": [
                    "Songs"
                ],
                "summary": "Delete a song",
                "operationId": "e345b004dde47c460287efce5237bacc",
                "parameters": [
                    {
                        "name": "id",
                        "in": "path",
                        "description": "Song ID",
                        "required": true,
                        "schema": {
                            "type": "integer"
                        }
                    }
                ],
                "responses": {
                    "200": {
                        "description": "Song deleted successfully",
                        "content": {
                            "application/json": {
                                "schema": {
                                    "properties": {
                                        "message": {
                                            "type": "string",
                                            "example": "Song Deleted Successfully"
                                        }
                                    },
                                    "type": "object"
                                }
                            }
                        }
                    },
                    "404": {
                        "description": "Song not found"
                    }
                },
                "security": [
                    {
                        "bearerAuth": []
                    }
                ]
            }
        },
        "/songs/search": {
            "get": {
                "tags": [
                    "Songs"
                ],
                "summary": "Search songs by title or artist",
                "operationId": "486ea09f311b6528edc8cbe1d46f21a8",
                "parameters": [
                    {
                        "name": "title",
                        "in": "query",
                        "description": "Search by song title",
                        "required": false,
                        "schema": {
                            "type": "string"
                        }
                    },
                    {
                        "name": "artist",
                        "in": "query",
                        "description": "Search by artist name",
                        "required": false,
                        "schema": {
                            "type": "string"
                        }
                    }
                ],
                "responses": {
                    "200": {
                        "description": "Success",
                        "content": {
                            "application/json": {
                                "schema": {
                                    "properties": {
                                        "data": {
                                            "type": "array",
                                            "items": {
                                                "properties": {
                                                    "id": {
                                                        "type": "integer",
                                                        "example": 1
                                                    },
                                                    "title": {
                                                        "type": "string",
                                                        "example": "Song Title"
                                                    },
                                                    "duration": {
                                                        "type": "integer",
                                                        "example": 180
                                                    }
                                                },
                                                "type": "object"
                                            }
                                        },
                                        "current_page": {
                                            "type": "integer",
                                            "example": 1
                                        },
                                        "per_page": {
                                            "type": "integer",
                                            "example": 10
                                        }
                                    },
                                    "type": "object"
                                }
                            }
                        }
                    },
                    "404": {
                        "description": "No songs found"
                    }
                },
                "security": [
                    {
                        "bearerAuth": []
                    }
                ]
            }
        }
    },
    "components": {
        "securitySchemes": {
            "bearerAuth": {
                "type": "http",
                "scheme": "bearer"
            }
        }
    },
    "tags": [
        {
            "name": "Albums",
            "description": "API Endpoints for Albums"
        },
        {
            "name": "Artists",
            "description": "API Endpoints for Artists"
        },
        {
            "name": "Authentication",
            "description": "API Endpoints for Authentication"
        },
        {
            "name": "Songs",
            "description": "API Endpoints for Songs"
        }
    ]
}